README.md
setup.py
linkedin_accept_invitation/__init__.py
linkedin_accept_invitation.egg-info/PKG-INFO
linkedin_accept_invitation.egg-info/SOURCES.txt
linkedin_accept_invitation.egg-info/dependency_links.txt
linkedin_accept_invitation.egg-info/requires.txt
linkedin_accept_invitation.egg-info/top_level.txt