Metadata-Version: 2.1
Name: linkedin-accept-invitation
Version: 1.0.0
Summary: A python library to accept invitations on linkedin automatically.
Home-page: https://linkedin-api.datakund.com/en/latest/
Author: DataKund
Author-email: datakund@gmail.com
License: Apache License 2.0
Keywords: linkedin python bot_studio automation invitation accept login
Platform: UNKNOWN
